llama_index/py.typed
llama_index/vector_stores/azureaisearch/__init__.py
llama_index/vector_stores/azureaisearch/azureaisearch_utils.py
llama_index/vector_stores/azureaisearch/base.py
llama_index_vector_stores_azureaisearch-0.4.3.dist-info/METADATA
llama_index_vector_stores_azureaisearch-0.4.3.dist-info/WHEEL
llama_index_vector_stores_azureaisearch-0.4.3.dist-info/licenses/LICENSE
llama_index_vector_stores_azureaisearch-0.4.3.dist-info/RECORD
