Metadata-Version: 2.4
Name: llama-index-vector-stores-azureaisearch
Version: 0.4.3
Summary: llama-index vector_stores azureaisearch integration
Author-email: Your Name <you@example.com>
License-Expression: MIT
License-File: LICENSE
Requires-Python: <4.0,>=3.9
Requires-Dist: azure-search-documents<12,>=11.5.1
Requires-Dist: llama-index-core<0.15,>=0.13.0
